{"GoBonusPopup_Count":"\u000e\u0002\u0005\u0004\u0000촁歩\u0000","SnorlaxRankListPopup_RankTitle_Best":"過去最高の評価 - \u000e\u0003\u0007\u0004Ā촀\u0000","SnorlaxRankListCell_NeedEnergyNum":"\u000e\u0002\u0007\u0004\u0000촁\u0000","ItemSelectCell_Num":"\u000e\u0002\u0003\u0004\u0000촁\u0000","SnorlaxRankListPopup_Title":"カビゴン評価の一覧\u0000","CampSetPopup_ToShopButton":"ショップへ\u0000","HomeScenePokemonBoxFullPopup_MoveButton":"ボックスへ\u0000","SleepDataDiscardPopup_Message":"未報告の状態で、30日間以上\n経過した睡眠データが\n破棄されました\u0000","SnorlaxRankupCutin_RewardNum":"x \u000e\u0002\u0005\u0004\u0000촁\u0000","LevelUpText":"LEVEL UP！\u0000","StorehouseNotificationCell_Num":"\u000e\u0002\u0002\u0002\u0000\u0000","CampSetUsePopup_SubTitle":"いいキャンプセットを\nレンタルします\u0000","SnorlaxRankupDetailPopup_TypeNumStart":"?種類\u0000","SnorlaxRankupCutin_Desc":"カビゴン評価がランクアップしました\u0000","SnorlaxRankupDetailPopup_Title":"カビゴン評価・\u000e\u0003\u0007\u0004Ā촀\u0000","SnorlaxRankListCell_ClearLabel":"CLEAR\u0000","CampSetPopup_Title":"いいキャンプセット\u0000","CampSetPopup_UseButton":"使用する\u0000","GoBonusPopup_Headline":"達成した回数\u0000","SnorlaxRankListPopup_Title_2":"評価の一覧\u0000","CampSetPopup_Desc":"睡眠リサーチがより快適になるキャンプセットが\nチケット1枚で1週間レンタルできます\n( 効果時間:168時間 )\u0000","SnorlaxRankupDetailPopup_TypeNum":"\u000e\u0002\u0003\u0004\u0000촁種類\u0000","MenuLatestResearchPopup_Name":"発見した寝顔\u0000","CandyGet_Popup_Text":"\u000e\u0003\n\u0002촀が\n\u000e\u0003\u0003\u0004ȁ촀 x\u000e\u0002\u0001\u0002\u0003を見つけました\u0000","CampSetPopup_TicketNum_Label":"所持チケット\u0000","CampSetPopup_TicketNum_Value":"\u000e\u0002\u0002\u0002\u0000枚\u0000","GoBonusPopup_Title_2":"Pokémon GOで歩いた回数\u0000","MenuLatestResearchPopup_Num_2":"\u000e\u0002\u0003\u0004\u0000촁\u0000","CandyGet_Popup_Title":"アメの入手\u0000","GoBonusPopup_Title_3":"ポケストップを回した回数\u0000","MenuLatestResearchPopup_Num_3":"\u000e\u0002\u0004\u0004\u0000촁\u0000","SnorlaxRankupDetailPopup_TypeNumUnknown":"???\u0000","CampSetPopup_Desc_Notime":"睡眠リサーチがより快適になるキャンプセットが\nチケット1枚で1週間レンタルできます\u0000","SnorlaxRankupDetailPopup_TypeNumTotalStart":"合計 ?種類\u0000","HomeScenePokemonBoxFullPopup_Content_Title":"ポケモンボックスがいっぱいです\u0000","MenuLatestResearchPopup_Num":"\u000e\u0002\u0003\u0004\u0000촁\u0000","GoBonusPopup_Count_2":"\u000e\u0002\u0004\u0004\u0000촁回\u0000","CampSetPopup_EffectDesc_1":"睡眠リサーチで来るポケモンが1匹増え、\nそのポケモンはチャンス確定になります\u0000","CampSetPopup_EffectDesc_2":"なべの容量(食材の投入上限数)が 1.5倍\u0000","SnorlaxRankListPopup_RankTitle":"現在の評価 -\u0000","CampSetPopup_EffectDesc_3":"おてつだいスピードが 1.2倍\u0000","CampSetUsePopup_Num":"x \u000e\u0002\u0002\u0002\u0000\u0000","HomeScenePokemonBoxFullPopup_Content_Desc":"ボックスを拡張するか、\nポケモンを博士に送ってください\u0000","CampSetPopup_EffectDesc_4":"おてつだい所持上限が 1.2倍\u0000","ExpUpText":"+\u000e\u0002\u0001\u0002\u0000\u0000","SnorlaxRankupCutin_Title":"\u000e\u0003\u0007\u0004Ā촀に到達\u0000","SnorlaxRankListCell_NeedEnergyLabel":"必要エナジー:\u0000","SnorlaxRankupDetailPopup_Message":"ねむけパワーが強くなり\nこのフィールドで見られる\n寝顔の種類が増えたようです\u0000","SleepDataDiscardPopup_Title":"未報告の睡眠データの破棄\u0000","SnorlaxRankListCell_NeedEnergy":"必要エナジー - なし\u0000","SnorlaxRankListCell_RewardTitle":"報酬\u0000","SnorlaxRankListPopup_RankDesc":"エナジーが一定に達するとカビゴンの評価が\nアップし、新しいポケモンが眠りにくるように\nなることがあります\u0000","CampSetUsePopup_Desc":"チケットを使用してもよろしいですか？\u0000","GoBonusPopup_HeaderTitle":"特別なピカチュウのおてつだい\u0000","GoBonusPopup_GetButton":"GET\u0000","SnorlaxRankListCell_RewardNum":"\u000e\u0002\u0003\u0004\u0000촁\u0000","HomeScenePokemonBoxFullPopup_Header_Title":"容量オーバー\u0000","SnorlaxRankupDetailPopup_TypeNum_Add":"+\u000e\u0002\u0003\u0004\u0000촁種類\u0000","CampSetPopup_SectionHeader_Effect":"効果の一覧\u0000","SnorlaxRankupCutin_DescReward":"報酬を獲得しました\u0000","SnorlaxRankupDetailPopup_RankTitle":"\u000e\u0003\u0007\u0004Ā촀\u0000","GoBonusPopup_Title":"Pokémon GOボーナス\u0000","SnorlaxRankupDetailPopup_TypeNumTotal":"合計 \u000e\u0002\u0003\u0004\u0000촁種類\u0000","GoBonusPopup_Reward":"\u000e\u0003\u0003\u0004Ā촀 x\u000e\u0002\u0001\u0002\u0002個\u0000","MenuLatestResearchPopup_Title":"リサーチ結果\u0000","ItemSelectPopup_Title":"おこう\u0000","MenuLatestResearchPopup_Name_2":"リサーチEXP\u0000","MenuLatestResearchPopup_Name_3":"ゆめのかけら\u0000","SnorlaxRankListPopup_RankValue":"\u000e\u0003\u0007\u0004Ā촀\u0000","SnorlaxRankupCutin_Message":"カビゴン評価がアップしました！\u0000"}